{"title": "Mazmur 131", "book": "19", "bookname": "Mazmur", "chapter": "131", "chapter_count": "150", "verses": [{"number": "1", "title": "Menyerah kepada TUHAN", "text": "Nyanyian ziarah Daud. TUHAN, aku tidak tinggi hati, dan tidak memandang dengan sombong; aku tidak mengejar hal-hal yang terlalu besar atau hal-hal yang terlalu ajaib bagiku."}, {"number": "2", "text": "Sesungguhnya, aku telah menenangkan dan mendiamkan jiwaku; seperti anak yang disapih berbaring dekat ibunya, ya, seperti anak yang disapih jiwaku dalam diriku."}, {"number": "3", "text": "Berharaplah kepada TUHAN, hai Israel, dari sekarang sampai selama-lamanya!"}]}